gym_delta_robot_trampoline/__init__.py
gym_delta_robot_trampoline/envs/__init__.py
gym_delta_robot_trampoline/envs/delta_robot_trampoline_env.py
gym_delta_robot_trampoline/resources/__init__.py
gym_delta_robot_trampoline/resources/ball.py
gym_delta_robot_trampoline/resources/delta_robot_model.py
gym_delta_robot_trampoline/resources/delta_robot_pybullet.urdf
gym_delta_robot_trampoline/resources/delta_robot_trampoline.py
gym_delta_robot_trampoline-0.1.7.dist-info/LICENSE
gym_delta_robot_trampoline-0.1.7.dist-info/METADATA
gym_delta_robot_trampoline-0.1.7.dist-info/WHEEL
gym_delta_robot_trampoline-0.1.7.dist-info/top_level.txt
gym_delta_robot_trampoline-0.1.7.dist-info/RECORD
