Metadata-Version: 2.1
Name: gym-delta-robot-trampoline
Version: 0.1.7
Summary: An OpenAI Gym Env for Delta Robot
Home-page: https://github.com/RicoJia/gym-delta-robot-trampoline
Author: Rico Ruotong Jia
Author-email: ruotongjia2020@u.northwestern.edu
License: UNKNOWN
Platform: UNKNOWN
Classifier: Programming Language :: Python :: 3
Classifier: License :: OSI Approved :: BSD License
Classifier: Operating System :: OS Independent
Requires-Python: >=3.6
Requires-Dist: gym
Requires-Dist: pybullet
Requires-Dist: numpy
Requires-Dist: matplotlib
